lod/__init__.py
lod/laugh.py
lod_domedi-0.0.dist-info/COPYING
lod_domedi-0.0.dist-info/LICENSE
lod_domedi-0.0.dist-info/METADATA
lod_domedi-0.0.dist-info/WHEEL
lod_domedi-0.0.dist-info/top_level.txt
lod_domedi-0.0.dist-info/RECORD
