Metadata-Version: 2.1
Name: lod-domedi
Version: 0.0
Summary: whatever
Home-page: https://github.com/EduardAlex/laughing-octo-doodle
Author: David Eduard
Author-email: edyalex.david@gmail.com
License: UNKNOWN
Platform: UNKNOWN
Classifier: Programming Language :: Python :: 3
Classifier: License :: Public Domain
Classifier: Operating System :: OS Independent
Requires-Python: >=3.6
